{
  "version": "5",
  "dialect": "pg",
  "entries": [
    {
      "idx": 0,
      "version": "5",
      "when": 1703428601196,
      "tag": "0000_eager_screwball",
      "breakpoints": true
    },
    {
      "idx": 1,
      "version": "5",
      "when": 1703519141646,
      "tag": "0001_damp_pride",
      "breakpoints": true
    },
    {
      "idx": 2,
      "version": "5",
      "when": 1703520951606,
      "tag": "0002_groovy_ikaris",
      "breakpoints": true
    },
    {
      "idx": 3,
      "version": "5",
      "when": 1704286665965,
      "tag": "0003_amused_namor",
      "breakpoints": true
    },
    {
      "idx": 4,
      "version": "5",
      "when": 1704310072125,
      "tag": "0004_spooky_shard",
      "breakpoints": true
    },
    {
      "idx": 5,
      "version": "5",
      "when": 1704313628150,
      "tag": "0005_bent_wind_dancer",
      "breakpoints": true
    },
    {
      "idx": 6,
      "version": "5",
      "when": 1704314608343,
      "tag": "0006_abandoned_prima",
      "breakpoints": true
    },
    {
      "idx": 7,
      "version": "5",
      "when": 1704370713979,
      "tag": "0007_unusual_mach_iv",
      "breakpoints": true
    }
  ]
}